spdx_lookup/__init__.py
spdx_lookup/__main__.py
spdx_lookup-0.3.3.dist-info/LICENSE
spdx_lookup-0.3.3.dist-info/METADATA
spdx_lookup-0.3.3.dist-info/WHEEL
spdx_lookup-0.3.3.dist-info/entry_points.txt
spdx_lookup-0.3.3.dist-info/top_level.txt
spdx_lookup-0.3.3.dist-info/RECORD
