Metadata-Version: 2.1
Name: spdx-lookup
Version: 0.3.3
Summary: SPDX license list query tool
Home-page: https://github.com/bbqsrc/spdx-lookup-python
Author: Brendan Molloy
Author-email: brendan+pypi@bbqsrc.net
License: BSD-2-Clause
Keywords: spdx,licenses,database,lookup,query
Platform: UNKNOWN
Classifier: Development Status :: 4 - Beta
Classifier: License :: OSI Approved :: BSD License
Classifier: Programming Language :: Python :: 2
Classifier: Programming Language :: Python :: 2.6
Classifier: Programming Language :: Python :: 2.7
Classifier: Programming Language :: Python :: 3
Classifier: Programming Language :: Python :: 3.2
Classifier: Programming Language :: Python :: 3.3
Classifier: Programming Language :: Python :: 3.4
Classifier: Programming Language :: Python :: 3.5
Requires-Dist: spdx (>=2.3.0)
